{"source": "Bigbasket", "iso_datetime": "2023-06-21T12:48:09.236799", "data": [{"name": "Onion", "qty": "1 kg", "mrp": "36.99", "sp": "24.50"}, {"name": "Tomato - Local", "qty": "500 g", "mrp": "32.19", "sp": "23.50"}, {"name": "Potato", "qty": "1 kg", "mrp": "46.58", "sp": "34.00"}, {"name": "Tender Coconut", "qty": "1 pc", "mrp": "72.60", "sp": "53.00"}, {"name": "Ladies' Fingers (Loose)", "qty": "1 kg", "mrp": "93.15", "sp": "38.00"}, {"name": "Fresho Pomegranate Regular", "qty": "1 kg", "mrp": "327.40", "sp": "239.00"}, {"name": "Cucumber (Loose)", "qty": "500 g", "mrp": "30.14", "sp": "22.00"}, {"name": "Cauliflower", "qty": "1 pc", "mrp": "49.32", "sp": "36.00"}, {"name": "Kiwi - Green", "qty": "3 pcs", "mrp": "169.86", "sp": "124.00"}, {"name": "Watermelon  - Small", "qty": "1 pc", "mrp": "124.66", "sp": "91.00"}, {"name": "Apple - Red Delicious, Economy", "qty": "4 pcs", "mrp": "217.81", "sp": "159.00"}, {"name": "Apple - Royal Gala, Regular", "qty": "4 pcs", "mrp": "279.45", "sp": "204.00"}, {"name": "Banana - Yelakki", "qty": "500 g", "mrp": "57.53", "sp": "39.00"}, {"name": "Sweet Corn", "qty": "2 pcs", "mrp": "63.01", "sp": "46.00"}, {"name": "Mosambi - Economy (Loose)", "qty": "1 kg", "mrp": "134.25", "sp": "98.00"}, {"name": "Garlic (Loose)", "qty": "250 g", "mrp": "89.04", "sp": "37.00"}, {"name": "Capsicum - Green (Loose)", "qty": "1 kg", "mrp": "164.46", "sp": "53.50"}, {"name": "Beans - Haricot (Loose)", "qty": "1 kg", "mrp": "200.00", "sp": "136.00"}, {"name": "Coconut - Medium", "qty": "1 pc", "mrp": "34.25", "sp": "25.00"}, {"name": "Cabbage", "qty": "1 pc", "mrp": "50.68", "sp": "29.50"}, {"name": "Lemon (Loose)", "qty": "250 g", "mrp": "47.95", "sp": "29.50"}, {"name": "Banana - Robusta", "qty": "500 g", "mrp": "29.45", "sp": "21.50"}, {"name": "Onion - Sambhar", "qty": "500 g", "mrp": "79.45", "sp": "51.00"}, {"name": "Apple - Red Delicious, Regular", "qty": "4 pcs", "mrp": "264.38", "sp": "150.00"}, {"name": "Mushrooms - Button", "qty": "1 pack", "mrp": "84.93", "sp": "62.00"}, {"name": "Chilli - Green Long, Medium (Loose)", "qty": "250 g", "mrp": "50.68", "sp": "24.50"}, {"name": "Ginger (Loose)", "qty": "250 g", "mrp": "105.48", "sp": "64.00"}, {"name": "Muskmelon -  Netted Small", "qty": "1 pc", "mrp": "63.01", "sp": "39.00"}, {"name": "Pomegranate", "qty": "4 pcs", "mrp": "304.11", "sp": "222.00"}, {"name": "Orange - Imported", "qty": "6 pcs", "mrp": "157.53", "sp": "115.00"}, {"name": "Banana - Nendran", "qty": "1 kg", "mrp": "115.07", "sp": "84.00"}, {"name": "Totapuri Mango", "qty": "1 kg", "mrp": "46.58", "sp": "34.00"}, {"name": "Sweet Potato (Loose)", "qty": "500 g", "mrp": "31.51", "sp": "20.50"}, {"name": "Indian Avocado (Loose)", "qty": "2 pcs", "mrp": "202.74", "sp": "148.00"}, {"name": "Guava (Loose)", "qty": "500 g", "mrp": "45.21", "sp": "33.00"}, {"name": "Banana - Red", "qty": "1 kg", "mrp": "130.14", "sp": "95.00"}, {"name": "Amla (Loose)", "qty": "100 g", "mrp": "16.99", "sp": "11.00"}, {"name": "Carrot - Ooty (Loose)", "qty": "500 g", "mrp": "84.25", "sp": "61.50"}, {"name": "Dates - Kimia, with Seed", "qty": "1 pc", "mrp": "254.79", "sp": "186.00"}, {"name": "Coriander Leaves", "qty": "1 kg", "mrp": "468.49", "sp": "342.00"}, {"name": "Coccinia (Loose)", "qty": "1 kg", "mrp": "73.97", "sp": "29.50"}, {"name": "Ooty Beetroot", "qty": "1 kg", "mrp": "115.07", "sp": "84.00"}, {"name": "Cucumber - English (Loose)", "qty": "1 kg", "mrp": "104.11", "sp": "76.00"}, {"name": "Orange - Imported", "qty": "4 pcs", "mrp": "105.48", "sp": "77.00"}, {"name": "Drumstick/Moringa", "qty": "250 g", "mrp": "32.88", "sp": "24.00"}, {"name": "Daily fruits combo", "qty": "Combo", "mrp": "320.54", "sp": "191.00"}, {"name": "Ooty Chow Chow", "qty": "500 g", "mrp": "39.73", "sp": "29.00"}, {"name": "Banana - Karpooravalli", "qty": "500 g", "mrp": "39.73", "sp": "29.00"}, {"name": "Curry Leaves", "qty": "100 g", "mrp": "17.81", "sp": "6.00"}, {"name": "Apple - Royal Gala Economy", "qty": "4 pcs", "mrp": "217.81", "sp": "159.00"}, {"name": "Mint Leaves - Cleaned, without roots", "qty": "1 kg", "mrp": "167.12", "sp": "122.00"}, {"name": "Brinjal - Nagpur (Loose)", "qty": "1 kg", "mrp": "87.67", "sp": "64.00"}, {"name": "Parwal (Loose)", "qty": "500 g", "mrp": "100.00", "sp": "73.00"}, {"name": "Onion - Organically Grown", "qty": "1 kg", "mrp": "50.68", "sp": "37.00"}, {"name": "Pineapple", "qty": "1 pc", "mrp": "84.93", "sp": "62.00"}, {"name": "Tomato - Hybrid", "qty": "1 kg", "mrp": "101.37", "sp": "66.50"}, {"name": "Baby Bottle Gourd", "qty": "1 pc, 300g - 450g", "mrp": "38.36", "sp": "28.00"}, {"name": "Mini Orange Imported", "qty": "500 g", "mrp": "221.92", "sp": "162.00"}, {"name": "Palak - Cleaned, without roots", "qty": "250 g", "mrp": "53.42", "sp": "39.00"}, {"name": "Papaya - Small", "qty": "1 pc", "mrp": "63.01", "sp": "46.00"}, {"name": "Bitter Gourd (Loose)", "qty": "1 kg", "mrp": "123.29", "sp": "90.00"}, {"name": "Banana - Hill", "qty": "500 g", "mrp": "32.88", "sp": "24.00"}, {"name": "Sweet Potato - Organically Grown (Loose)", "qty": "500 g", "mrp": "36.99", "sp": "27.00"}, {"name": "Avocado - Imported, Medium", "qty": "1 pc", "mrp": "113.70", "sp": "83.00"}, {"name": "Litchi", "qty": "1 kg", "mrp": "720.55", "sp": "526.00"}, {"name": "Apple - Green, Regular", "qty": "4 pcs Approx(500g-650g)", "mrp": "323.29", "sp": "236.00"}, {"name": "Colocasia (Loose)", "qty": "500 g", "mrp": "42.47", "sp": "28.00"}, {"name": "Raw Mango (Loose)", "qty": "1 kg", "mrp": "52.05", "sp": "38.00"}, {"name": "Banana - Raw Green (Loose)", "qty": "1 pc", "mrp": "21.92", "sp": "16.00"}, {"name": "Lettuce - Iceberg", "qty": "1 pc", "mrp": "101.37", "sp": "74.00"}, {"name": "Snake Gourd", "qty": "1 kg", "mrp": "71.23", "sp": "52.00"}, {"name": "Baby Banana - Robusta", "qty": "1 kg", "mrp": "52.05", "sp": "38.00"}, {"name": "Bottle Gourd", "qty": "1 pc", "mrp": "54.79", "sp": "40.00"}, {"name": "Spring Onion - With roots", "qty": "1 pc", "mrp": "36.99", "sp": "27.00"}, {"name": "Longan", "qty": "250 g", "mrp": "146.58", "sp": "107.00"}, {"name": "Beans - Cluster (Loose)", "qty": "250 g", "mrp": "35.62", "sp": "26.00"}, {"name": "Beetroot - Organically Grown (Loose)", "qty": "1 kg", "mrp": "82.19", "sp": "60.00"}, {"name": "Beans - Broad (Loose)", "qty": "500 g", "mrp": "82.19", "sp": "60.00"}, {"name": "Apple - Royal Gala, Premium", "qty": "4 pcs(Approx.600 g-700 g)", "mrp": "306.85", "sp": "224.00"}, {"name": "Yam - Elephant Foot", "qty": "500 g", "mrp": "75.34", "sp": "55.00"}, {"name": "Papaya - Medium", "qty": "1 pc", "mrp": "67.12", "sp": "49.00"}, {"name": "Cucumber - Organically Grown (Loose)", "qty": "500 g", "mrp": "34.25", "sp": "25.00"}, {"name": "Banana - Poovan", "qty": "500 g", "mrp": "41.10", "sp": "30.00"}, {"name": "Brinjal - Varikatri (Loose)", "qty": "500 g", "mrp": "60.27", "sp": "44.00"}, {"name": "Cabbage - Red", "qty": "500 g", "mrp": "68.49", "sp": "50.00"}, {"name": "Coconut - Large", "qty": "1 pc", "mrp": "41.10", "sp": "30.00"}, {"name": "Capsicum - Yellow, Organically Grown (Loose)", "qty": "1 pc", "mrp": "54.79", "sp": "40.00"}, {"name": "Mosambi (Loose)", "qty": "6 pcs", "mrp": "132.88", "sp": "97.00"}, {"name": "Organic Sprouts Mixed Gram", "qty": "200 g", "mrp": "43.84", "sp": "32.00"}, {"name": "Pumpkin - Green", "qty": "1 kg", "mrp": "56.16", "sp": "41.00"}, {"name": "Mosambi - Organically Grown (Loose)", "qty": "500 g", "mrp": "82.88", "sp": "60.50"}, {"name": "Ooty Potato - Medium", "qty": "1 kg", "mrp": "94.52", "sp": "69.00"}, {"name": "Rose - Red Flower", "qty": "250 g", "mrp": "53.42", "sp": "39.00"}, {"name": "Chrysanthemum/Shevanti Flower", "qty": "100 g", "mrp": "34.25", "sp": "25.00"}, {"name": "Capsicum - Red (Loose)", "qty": "2 pcs", "mrp": "54.79", "sp": "40.00"}, {"name": "Pear Beauty", "qty": "2 pcs", "mrp": "124.66", "sp": "91.00"}, {"name": "Baby Carrot (Loose)", "qty": "1 kg", "mrp": "117.81", "sp": "86.00"}, {"name": "Apple - Red Delicious, Premium", "qty": "4 pcs", "mrp": "312.33", "sp": "228.00"}, {"name": "Organic Sprouts Channa Brown", "qty": "200 g", "mrp": "39.73", "sp": "29.00"}, {"name": "Ash Gourd", "qty": "1 kg", "mrp": "52.05", "sp": "38.00"}, {"name": "Baby Corn - Unpeeled", "qty": "1 kg", "mrp": "101.37", "sp": "74.00"}, {"name": "Banana Stem", "qty": "1 pc", "mrp": "23.29", "sp": "17.00"}, {"name": "Organic Sprouts Moong Green", "qty": "200 g", "mrp": "46.58", "sp": "34.00"}, {"name": "Marigold Flower - Yellow", "qty": "100 g", "mrp": "10.96", "sp": "8.00"}, {"name": "Coconut - Organically Grown", "qty": "1 pc", "mrp": "47.95", "sp": "35.00"}, {"name": "Pidi Karanai (Loose)", "qty": "250 g", "mrp": "49.32", "sp": "36.00"}, {"name": "Amaranthus - Red Cleaned, without roots", "qty": "250 g", "mrp": "56.16", "sp": "41.00"}, {"name": "Cucumber - Mangalore, Organically Grown", "qty": "1 pc", "mrp": "76.71", "sp": "56.00"}, {"name": "Banana Flower - Organically Grown", "qty": "1 pc", "mrp": "42.47", "sp": "31.00"}, {"name": "Capsicum - Yellow (Loose)", "qty": "2 pcs", "mrp": "54.79", "sp": "40.00"}, {"name": "Lettuce - Red", "qty": "70 to 100 g (Bunch)", "mrp": "32.88", "sp": "24.00"}, {"name": "Tamarind - Sweet", "qty": "225 g", "mrp": "143.84", "sp": "105.00"}, {"name": "Zucchini - Green", "qty": "2 pcs Approx (300-400g)", "mrp": "98.63", "sp": "72.00"}, {"name": "Plum - Indian", "qty": "Approx 500 g", "mrp": "198.63", "sp": "145.00"}, {"name": "Marigold Flower - Orange", "qty": "250 g", "mrp": "23.29", "sp": "17.00"}, {"name": "Banana Flower", "qty": "1 pc", "mrp": "38.36", "sp": "28.00"}, {"name": "Apricot - Dried", "qty": "200 g", "mrp": "373.97", "sp": "273.00"}, {"name": "Banana Stem - Organically Grown", "qty": "1 pc", "mrp": "30.14", "sp": "22.00"}, {"name": "Betel Leaf", "qty": "5 pcs", "mrp": "13.70", "sp": "10.00"}, {"name": "Chinese Cabbage", "qty": "500 g", "mrp": "60.27", "sp": "44.00"}, {"name": "Mangosteen", "qty": "1 kg", "mrp": "600.00", "sp": "438.00"}, {"name": "Dry Copra/Coconut", "qty": "1 pc", "mrp": "56.16", "sp": "41.00"}, {"name": "Amaranthus - Green Cleaned, without roots", "qty": "250 g", "mrp": "56.16", "sp": "41.00"}, {"name": "Zucchini - Yellow", "qty": "2 pcs Approx (300-400g)", "mrp": "126.03", "sp": "92.00"}, {"name": "Jackfruit - Ripe", "qty": "250 g", "mrp": "73.97", "sp": "54.00"}, {"name": "Frozen Green Peas", "qty": "1 Kg", "mrp": "240.00", "sp": "189.00"}, {"name": "Ginger - Organically Grown (Loose)", "qty": "1 kg", "mrp": "413.70", "sp": "302.00"}, {"name": "Sambar Onion - Peeled (Small Onion)", "qty": "200 g", "mrp": "116.44", "sp": "85.00"}, {"name": "Tomato - Hybrid, Organically Grown (Loose)", "qty": "1 kg", "mrp": "93.15", "sp": "68.00"}, {"name": "Garlic - Peeled", "qty": "100 g", "mrp": "84.93", "sp": "40.00"}, {"name": "Fresh Almonds Green", "qty": "Approx 500 g", "mrp": "315.07", "sp": "230.00"}, {"name": "Aloe Vera - Organically grown (Loose)", "qty": "1 pc", "mrp": "56.16", "sp": "41.00"}, {"name": "Pineapple - Slices", "qty": "200 g", "mrp": "98.63", "sp": "48.00"}, {"name": "Ready to Cook - Potato French Fries", "qty": "200 g", "mrp": "43.84", "sp": "32.00"}, {"name": "Coconut Flower - Medium, Rich In Fibre, Helps Manage Blood Sugar Levels", "qty": "1 pc", "mrp": "69.86", "sp": "51.00"}, {"name": "Turmeric - Fresh (Loose)", "qty": "250 g", "mrp": "26.03", "sp": "19.00"}, {"name": "Frozen Sweet Corn", "qty": "1 kg", "mrp": "200.00", "sp": "149.00"}, {"name": "Kiwi - Dried", "qty": "200 g", "mrp": "235.62", "sp": "172.00"}, {"name": "Pumpkin - Organically Grown", "qty": "1 pc", "mrp": "116.44", "sp": "85.00"}, {"name": "Sugarcane", "qty": "1 pc", "mrp": "13.70", "sp": "10.00"}, {"name": "Pumpkin Green - Cut", "qty": "250 g", "mrp": "47.95", "sp": "18.00"}, {"name": "Banana - Hill", "qty": "1 kg", "mrp": "63.01", "sp": "46.00"}, {"name": "Mangosteen", "qty": "250 g", "mrp": "152.05", "sp": "111.00"}, {"name": "Bottle Gourd - Organically Grown", "qty": "1 pc", "mrp": "32.88", "sp": "24.00"}, {"name": "Mango - Neelam", "qty": "1 kg", "mrp": "117.81", "sp": "86.00"}, {"name": "Arai Keerai", "qty": "250 g", "mrp": "52.05", "sp": "38.00"}, {"name": "Neem Giloy (Amruta Balli) - Organically Grown", "qty": "100 g", "mrp": "26.03", "sp": "19.00"}, {"name": "Alternanthera Leaves/Ponnagenni Leaves - Cleaned, without roots", "qty": "250 g", "mrp": "38.36", "sp": "28.00"}, {"name": "Siru Keerai", "qty": "250 g", "mrp": "52.05", "sp": "38.00"}, {"name": "Pomegranate - Peeled", "qty": "200 g", "mrp": "172.60", "sp": "126.00"}, {"name": "Beans - French, Ring (Loose)", "qty": "1 kg", "mrp": "145.21", "sp": "106.00"}, {"name": "Capsicum - Red, Organically Grown (Loose)", "qty": "1 pc", "mrp": "54.79", "sp": "40.00"}, {"name": "Pea Eggplant / Sundaikai (Loose)", "qty": "100 g", "mrp": "13.70", "sp": "10.00"}, {"name": "Drumstick - Cut", "qty": "200 g", "mrp": "43.84", "sp": "32.00"}, {"name": "Ash Gourd - Cut", "qty": "250 g", "mrp": "46.58", "sp": "34.00"}, {"name": "Parsley Leaves - Curly", "qty": "100 g", "mrp": "31.51", "sp": "23.00"}, {"name": "Baby Corn - Peeled", "qty": "100 g", "mrp": "60.27", "sp": "44.00"}, {"name": "Pineapple - Chunks, Single Serve", "qty": "80 g", "mrp": "60.27", "sp": "44.00"}, {"name": "Gongura Leaves", "qty": "1 pc", "mrp": "46.58", "sp": "34.00"}, {"name": "Sweet Corn - Pellets", "qty": "250 g", "mrp": "89.04", "sp": "65.00"}, {"name": "Cabbage - Organically Grown", "qty": "1 pc (approx. 300-1.3 Kg)", "mrp": "63.01", "sp": "46.00"}, {"name": "Papaya- Diced", "qty": "200 g", "mrp": "56.16", "sp": "41.00"}, {"name": "Beans - Julienne", "qty": "200 g", "mrp": "90.41", "sp": "66.00"}, {"name": "Coconut - Diced", "qty": "150 g", "mrp": "60.27", "sp": "44.00"}, {"name": "Banana Blossom - Peeled", "qty": "1 pc", "mrp": "53.42", "sp": "39.00"}, {"name": "Turnip (Loose)", "qty": "1 kg", "mrp": "93.15", "sp": "68.00"}, {"name": "Banana Stem - Diced", "qty": "200 g", "mrp": "41.10", "sp": "30.00"}, {"name": "Celery", "qty": "250 g", "mrp": "60.27", "sp": "44.00"}, {"name": "Carrot - Ooty (Loose)", "qty": "1 kg", "mrp": "165.75", "sp": "121.00"}, {"name": "Ladies\u2019 Fingers - Diced", "qty": "200 g", "mrp": "53.42", "sp": "39.00"}, {"name": "Yam - Diced", "qty": "200 g", "mrp": "83.56", "sp": "61.00"}, {"name": "Capsicum - Diced", "qty": "200 g", "mrp": "68.49", "sp": "50.00"}, {"name": "Beans - Organically Grown (Loose)", "qty": "1 kg", "mrp": "238.36", "sp": "174.00"}, {"name": "Yam - Sliced", "qty": "200 g", "mrp": "80.82", "sp": "59.00"}, {"name": "Beans - Diced", "qty": "200 g", "mrp": "86.30", "sp": "63.00"}, {"name": "Beans Cluster - Diced", "qty": "200 g", "mrp": "56.16", "sp": "41.00"}, {"name": "Coriander Leaves - Chopped", "qty": "100 g", "mrp": "64.38", "sp": "47.00"}, {"name": "Beetroot - With Leaves, Packed With Nutrients, Improves Blood Flow", "qty": "1 kg", "mrp": "101.37", "sp": "74.00"}, {"name": "Beetroot - Diced", "qty": "200 g", "mrp": "64.38", "sp": "47.00"}, {"name": "Organic Sprouts Horse Gram", "qty": "200 g", "mrp": "45.21", "sp": "33.00"}, {"name": "Coccinia - Julienne", "qty": "200 g", "mrp": "45.21", "sp": "33.00"}, {"name": "Leeks", "qty": "100 g", "mrp": "26.03", "sp": "19.00"}, {"name": "Yellow Pumpkin - Avial Cut", "qty": "200 g", "mrp": "43.84", "sp": "32.00"}, {"name": "Banana Leaf", "qty": "5 pcs", "mrp": "22.06", "sp": "16.10"}, {"name": "Lemon Grass", "qty": "100 g", "mrp": "24.66", "sp": "18.00"}, {"name": "Garlic Powder - Spices & Masalas", "qty": "50 g", "mrp": "99.00", "sp": "99.00"}, {"name": "Pizza Oregano - Enhances Flavour", "qty": "34 g", "mrp": "99.00", "sp": "99.00"}, {"name": "Pea Eggplant / Sundaikai", "qty": "1 kg", "mrp": "371.06", "sp": "296.85"}, {"name": "Garlic - Peeled", "qty": "1 kg", "mrp": "616.25", "sp": "616.25"}, {"name": "Romania Mango", "qty": "1 kg", "mrp": "73.97", "sp": "54.00"}, {"name": "Jackfruit - Pulp", "qty": "1 kg", "mrp": "87.67", "sp": "64.00"}, {"name": "Red Cabbage - Grated", "qty": "200 g", "mrp": "67.12", "sp": "49.00"}, {"name": "Ridge Gourd - Sliced", "qty": "200 g", "mrp": "47.95", "sp": "35.00"}, {"name": "Beans - Double (Loose)", "qty": "500 g", "mrp": "105.48", "sp": "77.00"}, {"name": "Dates Fresh - Yellow", "qty": "500 g", "mrp": "241.10", "sp": "176.00"}, {"name": "Zespri Kiwi - Sun Gold", "qty": "3 pcs", "mrp": "322.91", "sp": "235.72"}, {"name": "Pak Choi", "qty": "250 g", "mrp": "41.10", "sp": "30.00"}, {"name": "Galangal", "qty": "1 kg", "mrp": "776.71", "sp": "567.00"}, {"name": "Cut - Mushroom", "qty": "100 g", "mrp": "82.19", "sp": "60.00"}, {"name": "Onion - Diced", "qty": "200 g", "mrp": "41.10", "sp": "30.00"}, {"name": "Bitter Gourd - Diced", "qty": "200 g", "mrp": "69.86", "sp": "51.00"}, {"name": "Cucumber - Sliced", "qty": "200 g", "mrp": "42.47", "sp": "31.00"}, {"name": "Green Cabbage - Grated", "qty": "200 g", "mrp": "43.84", "sp": "32.00"}, {"name": "Banana - Raw, Diced", "qty": "200 g", "mrp": "64.38", "sp": "47.00"}, {"name": "Banana - Raw, Sliced", "qty": "200 g", "mrp": "64.38", "sp": "47.00"}, {"name": "Bottle Gourd - Diced", "qty": "200 g", "mrp": "46.58", "sp": "34.00"}, {"name": "Chow Chow - Diced", "qty": "300 g", "mrp": "65.75", "sp": "48.00"}, {"name": "Thyme", "qty": "100 g", "mrp": "84.93", "sp": "62.00"}, {"name": "Snake gourd - Diced", "qty": "300 g", "mrp": "50.68", "sp": "37.00"}, {"name": "Coccinia - Sliced", "qty": "200 g", "mrp": "45.21", "sp": "33.00"}, {"name": "Ridge Gourd - Diced", "qty": "300 g", "mrp": "57.53", "sp": "42.00"}, {"name": "Papaya - Raw", "qty": "1 pc", "mrp": "64.38", "sp": "47.00"}, {"name": "Jamun", "qty": "250 g", "mrp": "53.42", "sp": "39.00"}, {"name": "Mint - Chopped", "qty": "100 g", "mrp": "38.36", "sp": "28.00"}, {"name": "Fresh Dates - Red", "qty": "500 g", "mrp": "224.66", "sp": "164.00"}, {"name": "Yam - Cut", "qty": "250 g", "mrp": "89.04", "sp": "65.00"}, {"name": "Kale - Curled, American", "qty": "1 pc", "mrp": "50.68", "sp": "37.00"}, {"name": "Sambar Onion - Peeled", "qty": "1 kg", "mrp": "524.66", "sp": "383.00"}, {"name": "Sugarcane - Diced", "qty": "200 g", "mrp": "42.47", "sp": "14.00"}, {"name": "Black Pepper Powder - No Added Colours & Preservatives", "qty": "50 g", "mrp": "139.00", "sp": "139.00"}, {"name": "Banganapalli Mango", "qty": "1 kg", "mrp": "117.81", "sp": "86.00"}, {"name": "Pear - Green, Imported", "qty": "2 pcs", "mrp": "113.70", "sp": "83.00"}, {"name": "Baby Potato (Loose)", "qty": "1 kg", "mrp": "87.67", "sp": "46.00"}, {"name": "Groundnut - Fresh (Loose)", "qty": "1 kg", "mrp": "142.47", "sp": "104.00"}, {"name": "Coriander Leaves 100 g + Garlic 250 g + Ginger 250 g + Chilli Green Long 250 g", "qty": "Combo", "mrp": "294.52", "sp": "161.50"}, {"name": "Dragon Fruit", "qty": "1 pc", "mrp": "109.59", "sp": "80.00"}, {"name": "Tomato - Local, Organically Grown (Loose)", "qty": "1 kg", "mrp": "80.82", "sp": "59.00"}, {"name": "Potato - Organically Grown", "qty": "1 kg", "mrp": "50.68", "sp": "37.00"}, {"name": "Brinjal - Purple, Long (Loose)", "qty": "1 kg", "mrp": "123.29", "sp": "90.00"}, {"name": "Lettuce - Green", "qty": "70 to 100 g (Bunch)", "mrp": "32.88", "sp": "24.00"}, {"name": "Ridge Gourd", "qty": "1 kg", "mrp": "79.45", "sp": "28.00"}, {"name": "Tomato - Green", "qty": "1 kg", "mrp": "65.75", "sp": "48.00"}, {"name": "Tomato - Hybrid 1kg + Onion 1kg + Potato 1kg (Organically Grown)", "qty": "Combo", "mrp": "194.51", "sp": "142.00"}, {"name": "Peach - Indian", "qty": "Approx 500 g", "mrp": "238.36", "sp": "174.00"}, {"name": "Broccoli", "qty": "1 pc", "mrp": "121.92", "sp": "83.00"}]}